stringking/__init__.py
stringking-0.0.1.dist-info/LICENSE
stringking-0.0.1.dist-info/METADATA
stringking-0.0.1.dist-info/WHEEL
stringking-0.0.1.dist-info/top_level.txt
stringking-0.0.1.dist-info/RECORD
