Metadata-Version: 2.1
Name: stringking
Version: 0.0.1
Summary: A package for string king developers.
Home-page: https://github.com/pypa/sampleproject
Author: Mike Schem
Author-email: mike@stringking.com
License: UNKNOWN
Project-URL: Bug Tracker, https://github.com/pypa/sampleproject/issues
Platform: UNKNOWN
Classifier: Programming Language :: Python :: 3
Classifier: License :: OSI Approved :: MIT License
Classifier: Operating System :: OS Independent
Requires-Python: >=3.6
